{
    "1678017578700498:2082": {
        "IResourceController": {
            "public": {
                "path": "UI/Resources/Scripts"
            }
        }
    },
    "1678017578701162:2466": {
        "IResourceController": {
            "name": "Scripts",
            "type": 0,
            "subtype": -1,
            "dependency": 0,
            "hidden": false,
            "publicId": "1678017578700498:2082",
            "resources": [
                "1678017578700098:1761",
                "1678017578700098:1762",
                "1678017578700098:1763",
                "1678017578700099:1764",
                "1678017578700099:1765",
                "1678017578700099:1766"
            ]
        }
    }
}
